cloudkitty/__init__.py
cloudkitty/config.py
cloudkitty/dataframe.py
cloudkitty/extension_manager.py
cloudkitty/i18n.py
cloudkitty/messaging.py
cloudkitty/orchestrator.py
cloudkitty/service.py
cloudkitty/state.py
cloudkitty/version.py
cloudkitty/write_orchestrator.py
cloudkitty/api/__init__.py
cloudkitty/api/app.py
cloudkitty/api/app.wsgi
cloudkitty/api/middleware.py
cloudkitty/api/root.py
cloudkitty/api/v1/__init__.py
cloudkitty/api/v1/config.py
cloudkitty/api/v1/hooks.py
cloudkitty/api/v1/types.py
cloudkitty/api/v1/controllers/__init__.py
cloudkitty/api/v1/controllers/collector.py
cloudkitty/api/v1/controllers/info.py
cloudkitty/api/v1/controllers/rating.py
cloudkitty/api/v1/controllers/report.py
cloudkitty/api/v1/controllers/storage.py
cloudkitty/api/v1/datamodels/__init__.py
cloudkitty/api/v1/datamodels/collector.py
cloudkitty/api/v1/datamodels/info.py
cloudkitty/api/v1/datamodels/rating.py
cloudkitty/api/v1/datamodels/report.py
cloudkitty/api/v1/datamodels/storage.py
cloudkitty/api/v2/__init__.py
cloudkitty/api/v2/base.py
cloudkitty/api/v2/utils.py
cloudkitty/api/v2/dataframes/__init__.py
cloudkitty/api/v2/dataframes/dataframes.py
cloudkitty/api/v2/rating/__init__.py
cloudkitty/api/v2/rating/modules.py
cloudkitty/api/v2/scope/__init__.py
cloudkitty/api/v2/scope/state.py
cloudkitty/api/v2/summary/__init__.py
cloudkitty/api/v2/summary/summary.py
cloudkitty/api/v2/task/__init__.py
cloudkitty/api/v2/task/reprocess.py
cloudkitty/backend/__init__.py
cloudkitty/backend/file.py
cloudkitty/cli/__init__.py
cloudkitty/cli/dbsync.py
cloudkitty/cli/processor.py
cloudkitty/cli/status.py
cloudkitty/cli/storage.py
cloudkitty/cli/writer.py
cloudkitty/collector/__init__.py
cloudkitty/collector/exceptions.py
cloudkitty/collector/gnocchi.py
cloudkitty/collector/prometheus.py
cloudkitty/common/__init__.py
cloudkitty/common/config.py
cloudkitty/common/context.py
cloudkitty/common/custom_session.py
cloudkitty/common/defaults.py
cloudkitty/common/policy.py
cloudkitty-23.0.0.dist-info/AUTHORS
cloudkitty-23.0.0.dist-info/LICENSE
cloudkitty-23.0.0.dist-info/METADATA
cloudkitty-23.0.0.dist-info/WHEEL
cloudkitty-23.0.0.dist-info/entry_points.txt
cloudkitty-23.0.0.dist-info/pbr.json
cloudkitty-23.0.0.dist-info/top_level.txt
cloudkitty-23.0.0.dist-info/RECORD
