Metadata-Version: 2.1
Name: cloudkitty
Version: 23.0.0
Summary: Rating as a Service component for OpenStack
Home-page: https://docs.openstack.org/cloudkitty/latest
Author: OpenStack
Author-email: openstack-discuss@lists.openstack.org
Classifier: Environment :: OpenStack
Classifier: Intended Audience :: Information Technology
Classifier: Intended Audience :: System Administrators
Classifier: License :: OSI Approved :: Apache Software License
Classifier: Operating System :: POSIX :: Linux
Classifier: Programming Language :: Python
Classifier: Programming Language :: Python :: 3
Classifier: Programming Language :: Python :: 3.10
Classifier: Programming Language :: Python :: 3.11
Classifier: Programming Language :: Python :: 3.12
Requires-Python: >=3.10
License-File: LICENSE
License-File: AUTHORS
Requires-Dist: pbr >=5.5.1
Requires-Dist: alembic >=1.4.3
Requires-Dist: keystonemiddleware >=9.1.0
Requires-Dist: gnocchiclient >=7.0.6
Requires-Dist: python-keystoneclient >=4.1.1
Requires-Dist: keystoneauth1 >=4.2.1
Requires-Dist: iso8601 >=0.1.13
Requires-Dist: PasteDeploy >=2.1.1
Requires-Dist: pecan >=1.3.3
Requires-Dist: WSME >=0.10.0
Requires-Dist: oslo.config >=8.3.3
Requires-Dist: oslo.context >=3.1.1
Requires-Dist: oslo.concurrency >=4.3.1
Requires-Dist: oslo.db >=8.4.0
Requires-Dist: oslo.i18n >=5.0.1
Requires-Dist: oslo.log >=4.4.0
Requires-Dist: oslo.messaging >=14.1.0
Requires-Dist: oslo.middleware >=4.1.1
Requires-Dist: oslo.policy >=4.5.0
Requires-Dist: oslo.utils >=4.7.0
Requires-Dist: oslo.upgradecheck >=1.3.0
Requires-Dist: python-dateutil >=2.8.0
Requires-Dist: SQLAlchemy >=1.3.20
Requires-Dist: stevedore >=3.2.2
Requires-Dist: tooz >=2.7.1
Requires-Dist: voluptuous >=0.12.0
Requires-Dist: influxdb >=5.3.1
Requires-Dist: influxdb-client >=1.36.0
Requires-Dist: Flask >=2.0.0
Requires-Dist: Flask-RESTful >=0.3.9
Requires-Dist: cotyledon >=1.7.3
Requires-Dist: futurist >=2.3.0
Requires-Dist: datetimerange >=0.6.1
Requires-Dist: requests >=2.14.2
